blurry/__init__.py
blurry/__main__.py
blurry/_nbdev.py
blurry/core.py
blurry/haarcascade_frontalface_default.xml
blurry/streamlit.py
blurry-0.0.5.dist-info/LICENSE
blurry-0.0.5.dist-info/METADATA
blurry-0.0.5.dist-info/WHEEL
blurry-0.0.5.dist-info/entry_points.txt
blurry-0.0.5.dist-info/top_level.txt
blurry-0.0.5.dist-info/RECORD
