Metadata-Version: 2.1
Name: blurry
Version: 0.0.5
Summary: Automatically blur faces in a photo for better privacy.
Home-page: https://github.com/JohannesStutz/blurry/tree/master/
Author: Johannes Stutz
Author-email: johannesstutz@gmail.com
License: Apache Software License 2.0
Keywords: privacy,anonymization,photo editing
Platform: UNKNOWN
Classifier: Development Status :: 3 - Alpha
Classifier: Intended Audience :: Developers
Classifier: License :: OSI Approved :: Apache Software License
Classifier: Natural Language :: English
Classifier: Programming Language :: Python :: 3.6
Classifier: Programming Language :: Python :: 3.7
Classifier: Programming Language :: Python :: 3.8
Requires-Python: >=3.6
Requires-Dist: opencv-python
Requires-Dist: Pillow
Requires-Dist: matplotlib
